dtype/__init__.py
dtype-0.0.11.dist-info/METADATA
dtype-0.0.11.dist-info/WHEEL
dtype-0.0.11.dist-info/top_level.txt
dtype-0.0.11.dist-info/RECORD
