Metadata-Version: 2.1
Name: dtype
Version: 0.0.11
Summary: dtype
Home-page: https://github.com/flowa-ai/dtype
Author: flowa
Author-email: flowa.ai@gmail.com
License: MIT
